{
  "name": "History-I",
  "tree": {
    "$className": "DataModel",

    "ReplicatedStorage": {
      "Packages": {
        "$path": "Packages"
      },

      "Shared": {
        "$path": "Match/shared"
      }
    },

    "ServerScriptService": {
      "Server": {
        "$path": "Match/server"
      }
    },

    "StarterPlayer": {
      "$properties": {
        "DevTouchMovementMode": "Thumbstick"
      },

      "StarterPlayerScripts": {
        "Client": {
          "$path": "Match/client"
        }
      }
    }
  }
}
